{"6min": {"1maj": 577, "2min": 500, "4maj": 1244, "5maj": 608, "b7maj": 121, "2maj7": 127, "3min": 375, "2maj": 118}, "1maj": {"6min": 1855, "4maj": 5220, "1maj7": 460, "5maj7": 671, "b7maj": 1133, "5maj": 2591, "4sus": 101, "3min": 428, "2min": 1370, "5min": 210, "1min": 129, "1sus": 288, "5sus": 259, "4min": 233, "2maj": 258, "b6maj": 162, "b3maj": 282, "2maj7": 119}, "2maj": {"5maj": 244, "1maj": 210}, "5maj": {"1maj": 3828, "4maj": 2165, "2min": 321, "6min": 557, "1min": 178, "b7maj": 167, "2maj": 166, "5maj7": 156, "3min": 208}, "4maj": {"1maj": 5748, "b7maj": 440, "3min": 432, "5maj": 3277, "5maj7": 398, "2min": 486, "1maj7": 212, "6min": 428, "4min": 212, "b3maj": 189, "b6maj": 103, "1min": 290, "5sus": 459, "4sus": 106}, "3maj7": {"6min": 176}, "2min": {"5maj7": 464, "3min": 255, "1maj": 771, "4maj": 613, "5maj": 623, "6min": 136, "5sus": 348, "b7maj": 169}, "5maj7": {"1maj": 1595, "1min": 401, "1maj7": 150, "4maj7": 165, "4maj": 180}, "1maj7": {"4maj": 566, "4maj7": 311, "1maj": 116, "5maj7": 208}, "b7maj": {"4maj": 1158, "1min": 886, "1maj": 817, "b3maj": 182, "b6maj": 425, "4min": 128, "5min": 142}, "3min": {"2min": 415, "6min": 390, "4maj": 509, "5maj": 100, "1maj": 115}, "4sus": {"4maj": 147}, "5min": {"1maj": 185, "4min": 132, "4maj": 148, "1min": 225, "b6maj": 174}, "4maj7": {"1maj7": 386, "1maj": 146, "1min": 175}, "1min": {"b6maj": 685, "4min": 519, "4maj": 377, "b7maj": 680, "b3maj": 270, "5min": 232, "4maj7": 172}, "b6maj": {"b7maj": 865, "b2maj": 100, "5min": 106, "5maj": 103, "1min": 256, "5maj7": 205, "b3maj": 221}, "4min": {"b3maj": 132, "b6maj": 187, "5min": 212, "1min": 309, "1maj": 345}, "b3maj": {"b6maj": 226, "b7maj": 320, "1min": 157, "4min": 126, "4maj": 389}, "1sus": {"1maj": 392}, "5sus": {"1maj": 737, "4maj": 128, "5maj7": 141, "5maj": 265}, "6maj": {"2maj": 107}, "b7maj5": {"1maj5": 115}, "1maj5": {"b7maj5": 146}, "6maj7": {"2min": 147}, "2maj7": {"5maj7": 177}, "4maj1": {"1maj1": 142}, "1maj1": {"4maj1": 155, "b7maj1": 143}, "b7maj1": {"1maj1": 162}}